[
  {
    "id": "169a8590-92c9-4484-b913-eb2bd6ad94f4",
    "Name": "Am interested in people",
    "Property": "",
    "Tags": "Agreeable/Assertive",
    "Number": ""
  },
  {
    "id": "177baf29-1253-46a3-b621-bd9125510fd2",
    "Name": "Make safety a top priority",
    "Property": "",
    "Tags": "Emotional Stability/Low Stress Tolerance",
    "Number": ""
  },
  {
    "id": "5b9e69d2-0e10-40dc-a257-b4c3619c4f46",
    "Name": "Am not a martyr",
    "Property": "",
    "Tags": "Agreeable/Assertive",
    "Number": ""
  },
  {
    "id": "761d29f5-6685-49cd-851e-8be236773c73",
    "Name": "Will confront people if necessary",
    "Property": "",
    "Tags": "Agreeable/Assertive",
    "Number": ""
  },
  {
    "id": "7fc5459b-ba54-4e7d-929d-81a8c9b8db8d",
    "Name": "Do not believe in change for the sake of change",
    "Property": "",
    "Tags": "Openness/Traditionalism",
    "Number": ""
  },
  {
    "id": "ced6c865-dac4-4142-963b-4cbc3b589e0b",
    "Name": "Do what I say I am going to do",
    "Property": "",
    "Tags": "Conscientiousness/Carelessness",
    "Number": ""
  },
  {
    "id": "09e59bff-2a6b-4d94-9f4c-ce7cb6fe8da4",
    "Name": "Get chores or tasks done right away",
    "Property": "",
    "Tags": "Conscientiousness/Carelessness",
    "Number": ""
  },
  {
    "id": "22872e1a-0f89-4b68-920b-fcd3d8dc8416",
    "Name": "My higher levels of anxiety have kept me safer than some people I know",
    "Property": "",
    "Tags": "Emotional Stability/Low Stress Tolerance",
    "Number": ""
  },
  {
    "id": "24ce484f-6772-4893-9a36-e384b2fe2ed1",
    "Name": "Seldom do anything dangerous",
    "Property": "",
    "Tags": "Emotional Stability/Low Stress Tolerance",
    "Number": ""
  },
  {
    "id": "2a3f26cc-2c3b-4a63-b781-c6ea250b82ed",
    "Name": "Make people feel at ease",
    "Property": "",
    "Tags": "Agreeable/Assertive",
    "Number": ""
  },
  {
    "id": "2a916ace-5fd7-40a1-986f-43497b3f3832",
    "Name": "Am very careful with my sexual behavior",
    "Property": "",
    "Tags": "Emotional Stability/Low Stress Tolerance",
    "Number": ""
  },
  {
    "id": "2d28b1ac-94cc-46a8-af3d-ded38184e11b",
    "Name": "Always arrive at appointments early or on time",
    "Property": "",
    "Tags": "Conscientiousness/Carelessness",
    "Number": ""
  },
  {
    "id": "422f5a2b-8a73-4f78-b38a-0ae65e9c70fb",
    "Name": "Believe that the tried and true way is the right way",
    "Property": "",
    "Tags": "Openness/Traditionalism",
    "Number": ""
  },
  {
    "id": "4805b6fc-9863-4574-abb3-766da8e08c31",
    "Name": "Have excellent ideas",
    "Property": "",
    "Tags": "Openness/Traditionalism",
    "Number": ""
  },
  {
    "id": "619b5cf3-42bd-45a2-9bf6-39e5768e51cb",
    "Name": "Am always learning new things",
    "Property": "",
    "Tags": "Openness/Traditionalism",
    "Number": ""
  },
  {
    "id": "7a7f3dd6-35ea-4cf3-8cee-258d6174f5e4",
    "Name": "Seldom get disturbed or upset",
    "Property": "",
    "Tags": "Emotional Stability/Low Stress Tolerance",
    "Number": ""
  },
  {
    "id": "8b46bd9a-1c8b-4726-8322-17c69da420fb",
    "Name": "Am enthusiastic about new opportunities",
    "Property": "",
    "Tags": "Extraversion/Introversion",
    "Number": ""
  },
  {
    "id": "a3185a10-1b56-42ce-ad5a-f9b8ff0242fe",
    "Name": "Do not attract undue attention to myself",
    "Property": "",
    "Tags": "Extraversion/Introversion",
    "Number": ""
  },
  {
    "id": "af7ed300-1ddf-4340-bbcb-3ca56a25e533",
    "Name": "Let other people have the spotlight",
    "Property": "",
    "Tags": "Extraversion/Introversion",
    "Number": ""
  },
  {
    "id": "c4c8c607-a817-4011-be12-723b69d965f0",
    "Name": "Do things according to a plan",
    "Property": "",
    "Tags": "Conscientiousness/Carelessness",
    "Number": ""
  },
  {
    "id": "d084c18f-20e9-4736-b01f-d0a71513653c",
    "Name": "Feel comfortable around people",
    "Property": "",
    "Tags": "Extraversion/Introversion",
    "Number": ""
  },
  {
    "id": "db6026c2-f232-46ee-93e7-62f0d64b718a",
    "Name": "Am good at seeing beneath the surface of false good intentions",
    "Property": "",
    "Tags": "Agreeable/Assertive",
    "Number": ""
  },
  {
    "id": "ec99549b-37e7-468c-9aa1-24149a0c324f",
    "Name": "Am resistant to radical, dangerous thoughts",
    "Property": "",
    "Tags": "Openness/Traditionalism",
    "Number": ""
  },
  {
    "id": "04cb174f-5fb3-428b-a27a-df24a816f3ef",
    "Name": "Can always see new possibility in things",
    "Property": "",
    "Tags": "Openness/Traditionalism",
    "Number": ""
  },
  {
    "id": "0d9071f7-e249-41f4-9bb8-961e3995d292",
    "Name": "Am not afraid of new people or social situations",
    "Property": "",
    "Tags": "Emotional Stability/Low Stress Tolerance",
    "Number": ""
  },
  {
    "id": "1a54082e-29e9-4352-a349-66085349ceb5",
    "Name": "Can handle a lot of information",
    "Property": "",
    "Tags": "Openness/Traditionalism",
    "Number": ""
  },
  {
    "id": "1dd9b9b7-f19f-431a-9633-64a48b81e6ee",
    "Name": "Do not feel that I always have to be in control",
    "Property": "",
    "Tags": "Conscientiousness/Carelessness",
    "Number": ""
  },
  {
    "id": "33f14e53-c2d8-4b4f-b46a-96d54fdf693a",
    "Name": "Think before I act",
    "Property": "",
    "Tags": "Extraversion/Introversion",
    "Number": ""
  },
  {
    "id": "54c185c8-a4fe-4aaf-bde7-bd99a00b5676",
    "Name": "Have a relaxed, laid-back attitude",
    "Property": "",
    "Tags": "Conscientiousness/Carelessness",
    "Number": ""
  },
  {
    "id": "6eeab538-d08e-4848-b0e7-0f7d7ece968c",
    "Name": "Am rarely or never stopped from doing what I want by my fears",
    "Property": "",
    "Tags": "Emotional Stability/Low Stress Tolerance",
    "Number": ""
  },
  {
    "id": "832c17cd-5fe2-4731-a7e2-1510c93d2c97",
    "Name": "Carry the conversation to a higher level",
    "Property": "No",
    "Tags": "Openness/Traditionalism",
    "Number": ""
  },
  {
    "id": "877d97ec-8d5f-426a-93eb-740b3543ba81",
    "Name": "Spend time reflecting on things",
    "Property": "",
    "Tags": "Openness/Traditionalism",
    "Number": ""
  },
  {
    "id": "8864d937-47dc-41a9-9f64-f259463cf1cd",
    "Name": "Do not upset my parents or other cultural authorities with doubts and questions",
    "Property": "",
    "Tags": "Openness/Traditionalism",
    "Number": ""
  },
  {
    "id": "8b31b467-b4ee-4470-b331-35d8ca3fb58a",
    "Name": "Stick to what I know and am comfortable with",
    "Property": "",
    "Tags": "Emotional Stability/Low Stress Tolerance",
    "Number": ""
  },
  {
    "id": "8f437ef0-a872-4875-be8f-90b84acce415",
    "Name": "Feel at ease with people",
    "Property": "",
    "Tags": "Extraversion/Introversion",
    "Number": ""
  },
  {
    "id": "957b1ab9-202d-4889-bf3d-439f5ce46b7f",
    "Name": "Inquire genuinely about others' well-being",
    "Property": "",
    "Tags": "Agreeable/Assertive",
    "Number": ""
  },
  {
    "id": "b77d5757-dd2b-4c2f-9745-bc29b661299e",
    "Name": "Am a very loyal friend",
    "Property": "",
    "Tags": "Agreeable/Assertive",
    "Number": ""
  },
  {
    "id": "baad197e-9228-4f1c-b0d7-cb36bb36cc9f",
    "Name": "Take time out for others",
    "Property": "",
    "Tags": "Agreeable/Assertive",
    "Number": ""
  },
  {
    "id": "d4a5acc0-2976-4a5a-aa3c-74931a15592e",
    "Name": "Watch what I eat carefully",
    "Property": "",
    "Tags": "Emotional Stability/Low Stress Tolerance",
    "Number": ""
  },
  {
    "id": "d842dfd2-4cab-48ca-8900-424914278b30",
    "Name": "Am aware that malevolence exists in the world",
    "Property": "",
    "Tags": "Agreeable/Assertive",
    "Number": ""
  },
  {
    "id": "eb52523e-3c1e-40ea-bc22-05ccd122f47a",
    "Name": "Enjoy time in natural surroundings",
    "Property": "",
    "Tags": "Extraversion/Introversion",
    "Number": ""
  },
  {
    "id": "0e3fa7c0-2da5-46cd-b5ee-b275cbd9bd79",
    "Name": "Will go to the doctor's office if there seems to be something wrong with me",
    "Property": "",
    "Tags": "Emotional Stability/Low Stress Tolerance",
    "Number": ""
  },
  {
    "id": "1e434b4e-7d01-4069-a694-c6e535f6f7be",
    "Name": "Continue until everything is perfect",
    "Property": "",
    "Tags": "Conscientiousness/Carelessness",
    "Number": ""
  },
  {
    "id": "24a2f004-b183-4b36-a432-6868a3aae140",
    "Name": "Truly care about others",
    "Property": "",
    "Tags": "Agreeable/Assertive",
    "Number": ""
  },
  {
    "id": "4fc12214-5e35-4ef0-adc8-1bd1a6fcf81f",
    "Name": "Am never perfectionistic",
    "Property": "",
    "Tags": "Conscientiousness/Carelessness",
    "Number": ""
  },
  {
    "id": "502de2af-8ffb-4286-baba-2522cf66bfd8",
    "Name": "Do not impose a rigid set of standards on other people",
    "Property": "",
    "Tags": "Conscientiousness/Carelessness",
    "Number": ""
  },
  {
    "id": "55559385-6b99-4682-b585-bafaf28a7649",
    "Name": "Am a cautious, careful person",
    "Property": "",
    "Tags": "Emotional Stability/Low Stress Tolerance",
    "Number": ""
  },
  {
    "id": "682e1234-f2ae-46a6-bc57-8269430dad90",
    "Name": "Never follow fads",
    "Property": "",
    "Tags": "Openness/Traditionalism",
    "Number": ""
  },
  {
    "id": "7444087e-8a32-4a6f-8a6a-7c3386781aa3",
    "Name": "Seldom feel hurt",
    "Property": "",
    "Tags": "Emotional Stability/Low Stress Tolerance",
    "Number": ""
  },
  {
    "id": "9a983541-271f-4be5-bfa0-eba751319576",
    "Name": "Talk to a lot of different people at social occasions",
    "Property": "",
    "Tags": "Extraversion/Introversion",
    "Number": ""
  },
  {
    "id": "a1b1a053-66d6-4e49-a813-3ff690301d8b",
    "Name": "Am comfortable alone",
    "Property": "",
    "Tags": "Extraversion/Introversion",
    "Number": ""
  },
  {
    "id": "a8db89e9-a285-4b94-a967-50f006da52bf",
    "Name": "Am a down-to-earth person",
    "Property": "",
    "Tags": "Openness/Traditionalism",
    "Number": ""
  },
  {
    "id": "adf7246d-ed74-4c90-b539-9e4489068821",
    "Name": "Try not to introduce unnecessary change into my life",
    "Property": "",
    "Tags": "Openness/Traditionalism",
    "Number": ""
  },
  {
    "id": "bbbccf56-812c-4798-9bc3-e5754c250a95",
    "Name": "Do not party or socialize excessively",
    "Property": "",
    "Tags": "Extraversion/Introversion",
    "Number": ""
  },
  {
    "id": "c3088e7e-dc60-4fa6-80b1-f78809395aac",
    "Name": "Do not always have to be the center of attention",
    "Property": "",
    "Tags": "Extraversion/Introversion",
    "Number": ""
  },
  {
    "id": "c68e9ba0-0d8d-4b94-b401-0063a2e74860",
    "Name": "Can see when people are playing games",
    "Property": "",
    "Tags": "Agreeable/Assertive",
    "Number": ""
  },
  {
    "id": "c9e8faa0-2553-41e5-af77-6a7830dd2e37",
    "Name": "Am often happy",
    "Property": "",
    "Tags": "Extraversion/Introversion",
    "Number": ""
  },
  {
    "id": "e76d6f5e-6d85-49c2-9505-62ea7cc646fc",
    "Name": "Can listen well",
    "Property": "",
    "Tags": "Extraversion/Introversion",
    "Number": ""
  },
  {
    "id": "08f8ecd7-e11e-4f18-bb23-e3fd22a73e1f",
    "Name": "Am not judgemental",
    "Property": "",
    "Tags": "Conscientiousness/Carelessness",
    "Number": ""
  },
  {
    "id": "11356ec2-d0c1-4340-bd1f-80f1c3281e47",
    "Name": "Am very goal-oriented",
    "Property": "",
    "Tags": "Conscientiousness/Carelessness",
    "Number": ""
  },
  {
    "id": "1c4116a2-a07e-4d22-a64b-ccf91d099272",
    "Name": "Am very rarely taken advantage of",
    "Property": "",
    "Tags": "Agreeable/Assertive",
    "Number": ""
  },
  {
    "id": "22753cf8-e2b7-481a-9e46-73928c1515ee",
    "Name": "Strive for efficiency and economy",
    "Property": "",
    "Tags": "Conscientiousness/Carelessness",
    "Number": ""
  },
  {
    "id": "23b52a04-8dc2-4630-a33c-74fb5a9b90f6",
    "Name": "Don't rush into things before I feel comfortable",
    "Property": "",
    "Tags": "Emotional Stability/Low Stress Tolerance",
    "Number": ""
  },
  {
    "id": "45b858d6-ce94-4cf5-b442-82c9662681b1",
    "Name": "See the value in tradition and custom",
    "Property": "",
    "Tags": "Openness/Traditionalism",
    "Number": ""
  },
  {
    "id": "5a244d6c-e30a-4e7f-a9f5-963657778535",
    "Name": "Love children",
    "Property": "",
    "Tags": "Agreeable/Assertive",
    "Number": ""
  },
  {
    "id": "626c296a-4135-4487-b725-6f433476fc99",
    "Name": "Am sceptical",
    "Property": "",
    "Tags": "Agreeable/Assertive",
    "Number": ""
  },
  {
    "id": "70b587c9-6de9-4118-8738-01b4a83f36bb",
    "Name": "Am difficult to offend",
    "Property": "",
    "Tags": "Emotional Stability/Low Stress Tolerance",
    "Number": ""
  },
  {
    "id": "7d86f7fc-d91a-48b7-99b3-7cb5c5c974a2",
    "Name": "Do not dominate conversations",
    "Property": "",
    "Tags": "Extraversion/Introversion",
    "Number": ""
  },
  {
    "id": "bcb3bbaf-142e-4b17-99f5-2d42b8a03f3e",
    "Name": "Rarely get irritated or angry",
    "Property": "",
    "Tags": "Emotional Stability/Low Stress Tolerance",
    "Number": ""
  },
  {
    "id": "c077c3bd-e74b-4236-8d0e-2a6456460cfc",
    "Name": "Have a soft heart",
    "Property": "",
    "Tags": "Agreeable/Assertive",
    "Number": ""
  },
  {
    "id": "cc6466e6-f250-491a-a590-b5cf9cfa83f0",
    "Name": "Don't get caught up in my problems or blow things out of proportion",
    "Property": "",
    "Tags": "Emotional Stability/Low Stress Tolerance",
    "Number": ""
  },
  {
    "id": "e3d25ec9-fca5-47a1-b3a6-ad0c0cbf0a3e",
    "Name": "Trust people",
    "Property": "",
    "Tags": "Agreeable/Assertive",
    "Number": ""
  },
  {
    "id": "ef442d76-a86f-48a8-8272-296f68705698",
    "Name": "Know how to captivate people",
    "Property": "",
    "Tags": "Extraversion/Introversion",
    "Number": ""
  },
  {
    "id": "efee94d9-6cac-4016-9e6a-afccfcdd9050",
    "Name": "Have a very long attention span and can work without being distracted",
    "Property": "",
    "Tags": "Conscientiousness/Carelessness",
    "Number": ""
  },
  {
    "id": "f1401868-f27d-498a-b2fb-415f7c8cc47a",
    "Name": "Am a good peacemaker",
    "Property": "",
    "Tags": "Agreeable/Assertive",
    "Number": ""
  },
  {
    "id": "09f6d1ee-d9a4-4329-b3e3-065741c88673",
    "Name": "Don't mind being the center of attention",
    "Property": "",
    "Tags": "Extraversion/Introversion",
    "Number": ""
  },
  {
    "id": "19dbd58c-2abb-4c3f-bf78-f7699a6e557c",
    "Name": "Am protective and careful with little children",
    "Property": "",
    "Tags": "Emotional Stability/Low Stress Tolerance",
    "Number": ""
  },
  {
    "id": "1a6dce35-71d1-4fc9-984f-5c1648d64e2b",
    "Name": "Rarely or never suffer extreme anxiety, even when stressed",
    "Property": "",
    "Tags": "Emotional Stability/Low Stress Tolerance",
    "Number": ""
  },
  {
    "id": "1d917aef-517e-4e31-b68f-b3c62910bb16",
    "Name": "Easily start conversations",
    "Property": "",
    "Tags": "Extraversion/Introversion",
    "Number": ""
  },
  {
    "id": "33ad7df2-2353-4baf-81c7-c6eb7568a8d6",
    "Name": "Am skilled in handling social situations",
    "Property": "",
    "Tags": "Extraversion/Introversion",
    "Number": ""
  },
  {
    "id": "3fbd2bc4-a825-47ab-b955-9026686ebf76",
    "Name": "Am seldom or never bothered by strange thoughts or feelings",
    "Property": "",
    "Tags": "Openness/Traditionalism",
    "Number": ""
  },
  {
    "id": "4a3a8ad2-5235-4077-ba8a-cda87152bb83",
    "Name": "Never do more work than is necessary",
    "Property": "",
    "Tags": "Conscientiousness/Carelessness",
    "Number": ""
  },
  {
    "id": "60a3217a-1bf3-4d2d-a1af-cc1aac7a36f9",
    "Name": "Am philosophically inclined",
    "Property": "",
    "Tags": "Openness/Traditionalism",
    "Number": ""
  },
  {
    "id": "642706cd-5a87-4c6b-b792-bcd5a158f785",
    "Name": "Respect authority",
    "Property": "",
    "Tags": "Openness/Traditionalism",
    "Number": ""
  },
  {
    "id": "666d711c-dd2f-423c-a15b-04f1b9fa0686",
    "Name": "Make plans and stick to them",
    "Property": "",
    "Tags": "Conscientiousness/Carelessness",
    "Number": ""
  },
  {
    "id": "851d2ebf-7739-410e-917c-37b011390607",
    "Name": "Am exacting in my work",
    "Property": "",
    "Tags": "Conscientiousness/Carelessness",
    "Number": ""
  },
  {
    "id": "9cd53be5-cb45-485a-bd84-7e03b1ea0fc0",
    "Name": "Am seldom attracted by foolish, new-age ideas",
    "Property": "",
    "Tags": "Openness/Traditionalism",
    "Number": ""
  },
  {
    "id": "c083b621-48a0-4d13-b5b6-5738165d6622",
    "Name": "Am full of ideas",
    "Property": "",
    "Tags": "Openness/Traditionalism",
    "Number": ""
  },
  {
    "id": "c94e17c0-7393-46c5-b83c-fba02fb012d2",
    "Name": "Am not bothered when things don't go according to plan",
    "Property": "",
    "Tags": "Conscientiousness/Carelessness",
    "Number": ""
  },
  {
    "id": "cb0ba16d-9ac8-42ee-8bae-f0c971ab9987",
    "Name": "Have a rich vocabulary",
    "Property": "",
    "Tags": "Openness/Traditionalism",
    "Number": ""
  },
  {
    "id": "d36f75cb-29b6-407d-8584-b930f0b7c114",
    "Name": "Am not naively innocent",
    "Property": "",
    "Tags": "Agreeable/Assertive",
    "Number": ""
  },
  {
    "id": "dbe69cca-8b25-4037-8e79-08e55ee048c6",
    "Name": "Can be the life of the party",
    "Property": "No",
    "Tags": "Extraversion/Introversion",
    "Number": ""
  },
  {
    "id": "eaf90cc6-b88e-4270-a507-7490f86b3be2",
    "Name": "Am seldom bothered by disorder",
    "Property": "",
    "Tags": "Conscientiousness/Carelessness",
    "Number": ""
  },
  {
    "id": "028c538b-6db4-4705-8eb1-62f2bdd6f989",
    "Name": "Can be demanding when the circumstances warrant",
    "Property": "",
    "Tags": "Agreeable/Assertive",
    "Number": ""
  },
  {
    "id": "21214b16-77c8-4f58-a52e-3c5ad4835376",
    "Name": "Have a lot of insight into myself and others",
    "Property": "",
    "Tags": "Openness/Traditionalism",
    "Number": ""
  },
  {
    "id": "23f31dfc-c35e-4e25-b6c4-93ba4e7521d8",
    "Name": "Feel others' emotions",
    "Property": "",
    "Tags": "Agreeable/Assertive",
    "Number": ""
  },
  {
    "id": "2d3ff5d2-a0ef-4933-9d32-4ebb763865d4",
    "Name": "Like to invite people out or at home to socialize",
    "Property": "",
    "Tags": "Extraversion/Introversion",
    "Number": ""
  },
  {
    "id": "54012b73-7c59-45f4-8a4f-5418decde9d0",
    "Name": "Have seen my tendency for hard work pay off",
    "Property": "",
    "Tags": "Conscientiousness/Carelessness",
    "Number": ""
  },
  {
    "id": "656d131e-24ed-4bd8-b7f0-2f10bd812d7f",
    "Name": "Will stand up for myself",
    "Property": "",
    "Tags": "Agreeable/Assertive",
    "Number": ""
  },
  {
    "id": "6a36638a-3722-426a-b10b-76166cdf98f4",
    "Name": "Am rarely or never too loud",
    "Property": "",
    "Tags": "Extraversion/Introversion",
    "Number": ""
  },
  {
    "id": "6dc0240d-8508-4b8c-929e-c8fd971d21f7",
    "Name": "Am in control of my emotions",
    "Property": "",
    "Tags": "Emotional Stability/Low Stress Tolerance",
    "Number": ""
  },
  {
    "id": "85ec1fd2-5796-47e2-936e-f82157187ce6",
    "Name": "Am aware of potential trouble even when other people appear confident",
    "Property": "",
    "Tags": "Emotional Stability/Low Stress Tolerance",
    "Number": ""
  },
  {
    "id": "87085530-f6db-433a-8328-db9e70a9a37a",
    "Name": "Have a vivid imagination",
    "Property": "",
    "Tags": "Openness/Traditionalism",
    "Number": ""
  },
  {
    "id": "b9d3bd1e-16fc-4496-9d7b-549e10c1e9e0",
    "Name": "Catch on to things quickly",
    "Property": "",
    "Tags": "Openness/Traditionalism",
    "Number": ""
  },
  {
    "id": "c3120958-a1e0-458a-844b-19952a0cdd41",
    "Name": "Am entrepreneurial",
    "Property": "",
    "Tags": "Openness/Traditionalism",
    "Number": ""
  },
  {
    "id": "df1ff9d4-b94a-410a-939f-42d12fb288f9",
    "Name": "Do not spend my money on a whim",
    "Property": "",
    "Tags": "Extraversion/Introversion",
    "Number": ""
  },
  {
    "id": "e4d6c778-c373-47e2-abac-6a195cfbfe13",
    "Name": "Am not grandiose or arrogant",
    "Property": "",
    "Tags": "Extraversion/Introversion",
    "Number": ""
  },
  {
    "id": "e9db05a4-8dbd-4208-b415-5f86e3bebaa3",
    "Name": "Will not forgive easily if betrayed or deceived",
    "Property": "",
    "Tags": "Agreeable/Assertive",
    "Number": ""
  },
  {
    "id": "e9ecd1d0-5112-479b-b06e-fcf9098ad354",
    "Name": "Am a creative person",
    "Property": "",
    "Tags": "Openness/Traditionalism",
    "Number": ""
  },
  {
    "id": "eba33dba-96aa-452f-bd1d-9e58b1b8fc68",
    "Name": "Do not set my expectations too high",
    "Property": "",
    "Tags": "Conscientiousness/Carelessness",
    "Number": ""
  },
  {
    "id": "f6b84ff3-e974-449d-a6a8-406064817624",
    "Name": "Am extremely reliable",
    "Property": "",
    "Tags": "Conscientiousness/Carelessness",
    "Number": ""
  },
  {
    "id": "268864e0-6f87-4b29-b7b1-f6ff4e257f18",
    "Name": "Am always prepared",
    "Property": "",
    "Tags": "Conscientiousness/Carelessness",
    "Number": ""
  },
  {
    "id": "29b1e4e4-7a1b-43f8-ba59-1aa646d18bd7",
    "Name": "Rarely self-conscious, ashamed or embarrassed",
    "Property": "",
    "Tags": "Emotional Stability/Low Stress Tolerance",
    "Number": ""
  },
  {
    "id": "42b9701d-e526-4d93-a18b-4dfc8f77190b",
    "Name": "Can easily be spontaneous and enjoy the moment",
    "Property": "",
    "Tags": "Conscientiousness/Carelessness",
    "Number": ""
  },
  {
    "id": "42e5ee63-1e77-478c-a47f-ab5c30ad9ea1",
    "Name": "Am a very sensible person",
    "Property": "",
    "Tags": "Openness/Traditionalism",
    "Number": ""
  },
  {
    "id": "57d60049-5a57-4aba-96a0-76253ce5bcaf",
    "Name": "Am fun to be around",
    "Property": "",
    "Tags": "Extraversion/Introversion",
    "Number": ""
  },
  {
    "id": "5a5b8481-e3ba-4b8e-91d9-1ac359af0f3e",
    "Name": "Rarely complain or grumble about things",
    "Property": "",
    "Tags": "Emotional Stability/Low Stress Tolerance",
    "Number": ""
  },
  {
    "id": "76809ff8-086f-42ee-afdb-1dbbb5cff007",
    "Name": "Don't get too caught up in my work",
    "Property": "",
    "Tags": "Conscientiousness/Carelessness",
    "Number": ""
  },
  {
    "id": "91b9aa86-f309-49e7-8f6c-c3ece6838c45",
    "Name": "Feel enough shame if I do something stupid so I won't do it again",
    "Property": "No",
    "Tags": "Emotional Stability/Low Stress Tolerance",
    "Number": ""
  },
  {
    "id": "9bd0e787-939c-4fea-83b8-3ca6d7febec6",
    "Name": "Know how to comfort others",
    "Property": "No",
    "Tags": "Agreeable/Assertive",
    "Number": ""
  },
  {
    "id": "a18af400-ff36-473b-bebe-0a04a70a6c1e",
    "Name": "Do not always believe what people promise",
    "Property": "",
    "Tags": "Agreeable/Assertive",
    "Number": ""
  },
  {
    "id": "b5c4e923-75ad-478e-be8a-6bc051d71e7e",
    "Name": "Do not trust people too easily",
    "Property": "",
    "Tags": "Agreeable/Assertive",
    "Number": ""
  },
  {
    "id": "b9a5bfb5-19e4-4f3b-b859-7cbb44cebc4d",
    "Name": "Sympathize with others' feelings",
    "Property": "",
    "Tags": "Agreeable/Assertive",
    "Number": ""
  },
  {
    "id": "ba00f908-53d8-4a88-9715-8904720c3836",
    "Name": "Make other people laugh and have fun",
    "Property": "",
    "Tags": "Extraversion/Introversion",
    "Number": ""
  },
  {
    "id": "d14427bf-9c57-49c5-979f-ad99f0f57520",
    "Name": "Am not flighty or unpredictable",
    "Property": "",
    "Tags": "Openness/Traditionalism",
    "Number": ""
  },
  {
    "id": "e0bd5b6a-ce79-40f2-9b2e-7ae57ce603b8",
    "Name": "Work very well with other people on teams",
    "Property": "",
    "Tags": "Agreeable/Assertive",
    "Number": ""
  },
  {
    "id": "e8484bdb-6475-434e-80a0-d9e8c205f327",
    "Name": "Am not too uptight",
    "Property": "",
    "Tags": "Conscientiousness/Carelessness",
    "Number": ""
  },
  {
    "id": "ef080ac0-efd0-4631-b2c3-baea93807981",
    "Name": "Am not easily swayed by emotions that might be manipulative",
    "Property": "",
    "Tags": "Agreeable/Assertive",
    "Number": ""
  },
  {
    "id": "f895ad86-6c94-4982-8a46-3396838494e3",
    "Name": "Am cautious of good intentions before proof is offered",
    "Property": "",
    "Tags": "Agreeable/Assertive",
    "Number": ""
  },
  {
    "id": "1f51c25f-b4c3-4832-a529-d51813ff6e64",
    "Name": "Am relaxed most of the time",
    "Property": "",
    "Tags": "Emotional Stability/Low Stress Tolerance",
    "Number": ""
  },
  {
    "id": "2d52069e-0156-456d-adce-60a7ed21ea12",
    "Name": "Am quick to understand things",
    "Property": "",
    "Tags": "Openness/Traditionalism",
    "Number": ""
  },
  {
    "id": "34173d12-5465-4b6f-b3e8-174503776d8d",
    "Name": "Love order and regularity",
    "Property": "",
    "Tags": "Conscientiousness/Carelessness",
    "Number": ""
  },
  {
    "id": "3480463a-31e0-4f97-bb81-b01fb1185564",
    "Name": "Am rarely incautious",
    "Property": "",
    "Tags": "Emotional Stability/Low Stress Tolerance",
    "Number": ""
  },
  {
    "id": "3ec8ea45-87fc-4556-84da-c95170034f1f",
    "Name": "Am rarely impulsive",
    "Property": "",
    "Tags": "Extraversion/Introversion",
    "Number": ""
  },
  {
    "id": "42301291-a00c-46df-bc74-6c645293a7a1",
    "Name": "Live in the moment",
    "Property": "",
    "Tags": "Conscientiousness/Carelessness",
    "Number": ""
  },
  {
    "id": "575094dc-03c1-4b8d-b8a9-e934e0730192",
    "Name": "Don't waste my time thinking about little details",
    "Property": "",
    "Tags": "Conscientiousness/Carelessness",
    "Number": ""
  },
  {
    "id": "5f090d03-2ef3-4ab0-a4da-f27e674899d6",
    "Name": "Am on good terms with nearly everyone",
    "Property": "",
    "Tags": "Agreeable/Assertive",
    "Number": ""
  },
  {
    "id": "7b016f56-015f-4888-a206-330f3222cd97",
    "Name": "Am sometimes not afraid of things I should be afraid of",
    "Property": "",
    "Tags": "",
    "Number": ""
  },
  {
    "id": "83cc12e5-0254-4422-8096-ccb44d88284d",
    "Name": "Calm down quickly when I do get upset",
    "Property": "",
    "Tags": "Emotional Stability/Low Stress Tolerance",
    "Number": ""
  },
  {
    "id": "8ccc59e9-257d-41b8-9ebe-2f3f6285d738",
    "Name": "Am concerned that my parents or relatives approve of my decisions",
    "Property": "",
    "Tags": "Openness/Traditionalism",
    "Number": ""
  },
  {
    "id": "9c41159e-d454-4ca3-b35a-b56d3674023a",
    "Name": "Know how to go with the flow",
    "Property": "",
    "Tags": "Conscientiousness/Carelessness",
    "Number": ""
  },
  {
    "id": "c79f26dc-0841-4358-a6ce-1a2331010ebf",
    "Name": "Do not always talk about myself",
    "Property": "",
    "Tags": "Extraversion/Introversion",
    "Number": ""
  },
  {
    "id": "c81c6594-f7af-4a9c-a7b8-90990d3a988c",
    "Name": "Make friends easily",
    "Property": "",
    "Tags": "Extraversion/Introversion",
    "Number": ""
  },
  {
    "id": "cbe8d7aa-5099-4169-8a2b-8c655fa2e94d",
    "Name": "Stay out of places that might have dangerous people in them",
    "Property": "",
    "Tags": "Emotional Stability/Low Stress Tolerance",
    "Number": ""
  },
  {
    "id": "d802e89d-8c53-48a5-8dc5-8d289a7cee04",
    "Name": "Am stable in my moral beliefs",
    "Property": "",
    "Tags": "Openness/Traditionalism",
    "Number": ""
  },
  {
    "id": "eacaac29-a10f-4335-92dc-bce30aa4d4ac",
    "Name": "Am good at identifying the risks in new situations",
    "Property": "",
    "Tags": "Emotional Stability/Low Stress Tolerance",
    "Number": ""
  },
  {
    "id": "fbb9ced6-6515-4497-9e0a-021a3040026d",
    "Name": "Can take charge and lead",
    "Property": "",
    "Tags": "Extraversion/Introversion",
    "Number": ""
  },
  {
    "id": "159abc13-ec09-41b4-9333-d528938ea585",
    "Name": "Am content with my physical appearance, despite its flaws",
    "Property": "",
    "Tags": "Emotional Stability/Low Stress Tolerance",
    "Number": ""
  },
  {
    "id": "31994d20-6e83-4efc-a753-6ad8b4453f5c",
    "Name": "Do not always need to seek excitement or novelty",
    "Property": "",
    "Tags": "Extraversion/Introversion",
    "Number": ""
  },
  {
    "id": "48699850-5788-41fd-a2fb-33539ff620c7",
    "Name": "Pay attention to details",
    "Property": "",
    "Tags": "Conscientiousness/Carelessness",
    "Number": ""
  },
  {
    "id": "cbdee765-3049-441c-a28f-c0ea6b75ed18",
    "Name": "Seldom feel depressed or blue",
    "Property": "",
    "Tags": "Emotional Stability/Low Stress Tolerance",
    "Number": ""
  }
]